less/__init__.py
less/_utils.py
less/less.py
less_learn-0.4.0.dist-info/licenses/LICENSE
less_learn-0.4.0.dist-info/METADATA
less_learn-0.4.0.dist-info/WHEEL
less_learn-0.4.0.dist-info/top_level.txt
less_learn-0.4.0.dist-info/RECORD
