Metadata-Version: 2.4
Name: less-learn
Version: 0.4.0
Summary: Learning with Subset Stacking
Home-page: https://github.com/sibirbil/LESS
Author-email: Ilker Birbil <sibirbil@gmail.com>, Samet Copur <sametcopur@yahoo.com>
Maintainer: Ilker Birbil, Samet Çopur
Maintainer-email: s.i.birbil@uva.nl, sametcopur@yahoo.com
License: MIT License
Project-URL: Repository, https://github.com/sibirbil/LESS
Project-URL: Tracker, https://github.com/sibirbil/LESS/issues
Keywords: python,optimization,adaptive-random-search,hyperparameter-tuning,hyperparameter-optimization,mixed-parameter-space,categorical-parameters,machine-learning,data-science,metaheuristics
Classifier: Development Status :: 5 - Production/Stable
Classifier: Intended Audience :: Science/Research
Classifier: Intended Audience :: Developers
Classifier: License :: OSI Approved :: MIT License
Classifier: Programming Language :: Python :: 3
Classifier: Programming Language :: Python :: 3.8
Classifier: Programming Language :: Python :: 3.9
Classifier: Programming Language :: Python :: 3.10
Classifier: Programming Language :: Python :: 3.11
Classifier: Programming Language :: Python :: 3.12
Classifier: Programming Language :: Python :: 3.13
Classifier: Programming Language :: Python :: 3.14
Classifier: Programming Language :: Python :: 3 :: Only
Classifier: Topic :: Scientific/Engineering
Classifier: Topic :: Scientific/Engineering :: Mathematics
Classifier: Topic :: Scientific/Engineering :: Artificial Intelligence
Classifier: Topic :: Software Development
Classifier: Topic :: Software Development :: Libraries
Classifier: Topic :: Software Development :: Libraries :: Python Modules
Requires-Python: >=3.8
License-File: LICENSE
Requires-Dist: numpy
Requires-Dist: scikit-learn
Requires-Dist: xgboost
Provides-Extra: extra
Requires-Dist: scipy; extra == "extra"
Dynamic: home-page
Dynamic: license-file
Dynamic: maintainer
Dynamic: maintainer-email
Dynamic: requires-python
